mlb_love-0.1.0.dist-info/METADATA
mlb_love-0.1.0.dist-info/WHEEL
mlb_love/__init__.py
mlb_love-0.1.0.dist-info/RECORD
