Metadata-Version: 2.1
Name: mlb-love
Version: 0.1.0
Summary: MLB
Author-Email: rim01 <kylttop01@gmail.com>
License: MIT
Requires-Python: >=3.7
